{
  "generatedAt": "2025-11-13T21:35:00.432347+00:00",
  "seasonId": "20252026",
  "teams": [
    {
      "team": "Colorado Avalanche",
      "abbrev": "COL",
      "wins": 11,
      "losses": 1,
      "ot": 5,
      "points": 27,
      "gamesPlayed": 17,
      "pointPctg": 0.79411,
      "goalDifferential": 27,
      "goalsForPerGame": 4.0,
      "goalsAgainstPerGame": 2.41176,
      "shotsForPerGame": 34.05882,
      "shotsAgainstPerGame": 26.17647,
      "seasonId": 20252026
    },
    {
      "team": "New Jersey Devils",
      "abbrev": "NJD",
      "wins": 12,
      "losses": 4,
      "ot": 1,
      "points": 25,
      "gamesPlayed": 17,
      "pointPctg": 0.73529,
      "goalDifferential": 7,
      "goalsForPerGame": 3.35294,
      "goalsAgainstPerGame": 2.94117,
      "shotsForPerGame": 29.41176,
      "shotsAgainstPerGame": 27.7647,
      "seasonId": 20252026
    },
    {
      "team": "Anaheim Ducks",
      "abbrev": "ANA",
      "wins": 11,
      "losses": 4,
      "ot": 1,
      "points": 23,
      "gamesPlayed": 16,
      "pointPctg": 0.71875,
      "goalDifferential": 13,
      "goalsForPerGame": 3.9375,
      "goalsAgainstPerGame": 3.125,
      "shotsForPerGame": 30.5,
      "shotsAgainstPerGame": 30.375,
      "seasonId": 20252026
    },
    {
      "team": "Dallas Stars",
      "abbrev": "DAL",
      "wins": 10,
      "losses": 4,
      "ot": 3,
      "points": 23,
      "gamesPlayed": 17,
      "pointPctg": 0.67647,
      "goalDifferential": -2,
      "goalsForPerGame": 2.94117,
      "goalsAgainstPerGame": 3.05882,
      "shotsForPerGame": 26.17647,
      "shotsAgainstPerGame": 28.05882,
      "seasonId": 20252026
    },
    {
      "team": "Carolina Hurricanes",
      "abbrev": "CAR",
      "wins": 11,
      "losses": 5,
      "ot": 0,
      "points": 22,
      "gamesPlayed": 16,
      "pointPctg": 0.6875,
      "goalDifferential": 13,
      "goalsForPerGame": 3.6875,
      "goalsAgainstPerGame": 2.875,
      "shotsForPerGame": 33.25,
      "shotsAgainstPerGame": 26.6875,
      "seasonId": 20252026
    },
    {
      "team": "Boston Bruins",
      "abbrev": "BOS",
      "wins": 11,
      "losses": 7,
      "ot": 0,
      "points": 22,
      "gamesPlayed": 18,
      "pointPctg": 0.61111,
      "goalDifferential": 2,
      "goalsForPerGame": 3.38888,
      "goalsAgainstPerGame": 3.27777,
      "shotsForPerGame": 27.33333,
      "shotsAgainstPerGame": 30.05555,
      "seasonId": 20252026
    },
    {
      "team": "Montr\u00e9al Canadiens",
      "abbrev": "MTL",
      "wins": 10,
      "losses": 4,
      "ot": 2,
      "points": 22,
      "gamesPlayed": 16,
      "pointPctg": 0.6875,
      "goalDifferential": 7,
      "goalsForPerGame": 3.625,
      "goalsAgainstPerGame": 3.1875,
      "shotsForPerGame": 24.6875,
      "shotsAgainstPerGame": 27.0625,
      "seasonId": 20252026
    },
    {
      "team": "Pittsburgh Penguins",
      "abbrev": "PIT",
      "wins": 9,
      "losses": 5,
      "ot": 3,
      "points": 21,
      "gamesPlayed": 17,
      "pointPctg": 0.61764,
      "goalDifferential": 12,
      "goalsForPerGame": 3.35294,
      "goalsAgainstPerGame": 2.64705,
      "shotsForPerGame": 28.29411,
      "shotsAgainstPerGame": 29.58823,
      "seasonId": 20252026
    },
    {
      "team": "Winnipeg Jets",
      "abbrev": "WPG",
      "wins": 10,
      "losses": 6,
      "ot": 0,
      "points": 20,
      "gamesPlayed": 16,
      "pointPctg": 0.625,
      "goalDifferential": 10,
      "goalsForPerGame": 3.25,
      "goalsAgainstPerGame": 2.625,
      "shotsForPerGame": 27.1875,
      "shotsAgainstPerGame": 29.6875,
      "seasonId": 20252026
    },
    {
      "team": "Utah Mammoth",
      "abbrev": "UTA",
      "wins": 10,
      "losses": 7,
      "ot": 0,
      "points": 20,
      "gamesPlayed": 17,
      "pointPctg": 0.58823,
      "goalDifferential": 4,
      "goalsForPerGame": 3.29411,
      "goalsAgainstPerGame": 3.05882,
      "shotsForPerGame": 29.7647,
      "shotsAgainstPerGame": 23.70588,
      "seasonId": 20252026
    },
    {
      "team": "New York Rangers",
      "abbrev": "NYR",
      "wins": 9,
      "losses": 7,
      "ot": 2,
      "points": 20,
      "gamesPlayed": 18,
      "pointPctg": 0.55555,
      "goalDifferential": 2,
      "goalsForPerGame": 2.66666,
      "goalsAgainstPerGame": 2.55555,
      "shotsForPerGame": 27.66666,
      "shotsAgainstPerGame": 27.38888,
      "seasonId": 20252026
    },
    {
      "team": "Chicago Blackhawks",
      "abbrev": "CHI",
      "wins": 8,
      "losses": 5,
      "ot": 4,
      "points": 20,
      "gamesPlayed": 17,
      "pointPctg": 0.58823,
      "goalDifferential": 12,
      "goalsForPerGame": 3.29411,
      "goalsAgainstPerGame": 2.58823,
      "shotsForPerGame": 24.88235,
      "shotsAgainstPerGame": 31.82352,
      "seasonId": 20252026
    },
    {
      "team": "Los Angeles Kings",
      "abbrev": "LAK",
      "wins": 8,
      "losses": 5,
      "ot": 4,
      "points": 20,
      "gamesPlayed": 17,
      "pointPctg": 0.58823,
      "goalDifferential": 0,
      "goalsForPerGame": 2.88235,
      "goalsAgainstPerGame": 2.88235,
      "shotsForPerGame": 29.05882,
      "shotsAgainstPerGame": 27.35294,
      "seasonId": 20252026
    },
    {
      "team": "Ottawa Senators",
      "abbrev": "OTT",
      "wins": 8,
      "losses": 5,
      "ot": 4,
      "points": 20,
      "gamesPlayed": 17,
      "pointPctg": 0.58823,
      "goalDifferential": -4,
      "goalsForPerGame": 3.35294,
      "goalsAgainstPerGame": 3.58823,
      "shotsForPerGame": 27.41176,
      "shotsAgainstPerGame": 26.05882,
      "seasonId": 20252026
    },
    {
      "team": "Edmonton Oilers",
      "abbrev": "EDM",
      "wins": 8,
      "losses": 6,
      "ot": 4,
      "points": 20,
      "gamesPlayed": 18,
      "pointPctg": 0.55555,
      "goalDifferential": -6,
      "goalsForPerGame": 3.0,
      "goalsAgainstPerGame": 3.33333,
      "shotsForPerGame": 28.44444,
      "shotsAgainstPerGame": 25.05555,
      "seasonId": 20252026
    },
    {
      "team": "Philadelphia Flyers",
      "abbrev": "PHI",
      "wins": 8,
      "losses": 5,
      "ot": 3,
      "points": 19,
      "gamesPlayed": 16,
      "pointPctg": 0.59375,
      "goalDifferential": 0,
      "goalsForPerGame": 2.5625,
      "goalsAgainstPerGame": 2.5625,
      "shotsForPerGame": 24.5625,
      "shotsAgainstPerGame": 25.5,
      "seasonId": 20252026
    },
    {
      "team": "San Jose Sharks",
      "abbrev": "SJS",
      "wins": 8,
      "losses": 6,
      "ot": 3,
      "points": 19,
      "gamesPlayed": 17,
      "pointPctg": 0.55882,
      "goalDifferential": -1,
      "goalsForPerGame": 3.23529,
      "goalsAgainstPerGame": 3.29411,
      "shotsForPerGame": 24.58823,
      "shotsAgainstPerGame": 31.88235,
      "seasonId": 20252026
    },
    {
      "team": "Seattle Kraken",
      "abbrev": "SEA",
      "wins": 7,
      "losses": 4,
      "ot": 5,
      "points": 19,
      "gamesPlayed": 16,
      "pointPctg": 0.59375,
      "goalDifferential": -4,
      "goalsForPerGame": 2.5,
      "goalsAgainstPerGame": 2.75,
      "shotsForPerGame": 25.0625,
      "shotsAgainstPerGame": 27.6875,
      "seasonId": 20252026
    },
    {
      "team": "Detroit Red Wings",
      "abbrev": "DET",
      "wins": 9,
      "losses": 7,
      "ot": 0,
      "points": 18,
      "gamesPlayed": 16,
      "pointPctg": 0.5625,
      "goalDifferential": -7,
      "goalsForPerGame": 2.75,
      "goalsAgainstPerGame": 3.1875,
      "shotsForPerGame": 29.1875,
      "shotsAgainstPerGame": 27.0,
      "seasonId": 20252026
    },
    {
      "team": "New York Islanders",
      "abbrev": "NYI",
      "wins": 8,
      "losses": 6,
      "ot": 2,
      "points": 18,
      "gamesPlayed": 16,
      "pointPctg": 0.5625,
      "goalDifferential": 2,
      "goalsForPerGame": 3.3125,
      "goalsAgainstPerGame": 3.1875,
      "shotsForPerGame": 29.625,
      "shotsAgainstPerGame": 29.125,
      "seasonId": 20252026
    },
    {
      "team": "Tampa Bay Lightning",
      "abbrev": "TBL",
      "wins": 8,
      "losses": 6,
      "ot": 2,
      "points": 18,
      "gamesPlayed": 16,
      "pointPctg": 0.5625,
      "goalDifferential": 1,
      "goalsForPerGame": 3.0625,
      "goalsAgainstPerGame": 3.0,
      "shotsForPerGame": 26.875,
      "shotsAgainstPerGame": 28.5,
      "seasonId": 20252026
    },
    {
      "team": "Vegas Golden Knights",
      "abbrev": "VGK",
      "wins": 7,
      "losses": 4,
      "ot": 4,
      "points": 18,
      "gamesPlayed": 15,
      "pointPctg": 0.6,
      "goalDifferential": 4,
      "goalsForPerGame": 3.2,
      "goalsAgainstPerGame": 2.93333,
      "shotsForPerGame": 29.66666,
      "shotsAgainstPerGame": 25.46666,
      "seasonId": 20252026
    },
    {
      "team": "Minnesota Wild",
      "abbrev": "MIN",
      "wins": 7,
      "losses": 7,
      "ot": 4,
      "points": 18,
      "gamesPlayed": 18,
      "pointPctg": 0.5,
      "goalDifferential": -9,
      "goalsForPerGame": 2.77777,
      "goalsAgainstPerGame": 3.27777,
      "shotsForPerGame": 28.5,
      "shotsAgainstPerGame": 29.61111,
      "seasonId": 20252026
    },
    {
      "team": "Washington Capitals",
      "abbrev": "WSH",
      "wins": 8,
      "losses": 7,
      "ot": 1,
      "points": 17,
      "gamesPlayed": 16,
      "pointPctg": 0.53125,
      "goalDifferential": 8,
      "goalsForPerGame": 2.875,
      "goalsAgainstPerGame": 2.375,
      "shotsForPerGame": 29.25,
      "shotsAgainstPerGame": 25.625,
      "seasonId": 20252026
    },
    {
      "team": "Columbus Blue Jackets",
      "abbrev": "CBJ",
      "wins": 8,
      "losses": 7,
      "ot": 1,
      "points": 17,
      "gamesPlayed": 16,
      "pointPctg": 0.53125,
      "goalDifferential": -3,
      "goalsForPerGame": 3.0,
      "goalsAgainstPerGame": 3.1875,
      "shotsForPerGame": 32.125,
      "shotsAgainstPerGame": 31.5625,
      "seasonId": 20252026
    },
    {
      "team": "Toronto Maple Leafs",
      "abbrev": "TOR",
      "wins": 8,
      "losses": 8,
      "ot": 1,
      "points": 17,
      "gamesPlayed": 17,
      "pointPctg": 0.5,
      "goalDifferential": -3,
      "goalsForPerGame": 3.64705,
      "goalsAgainstPerGame": 3.82352,
      "shotsForPerGame": 28.17647,
      "shotsAgainstPerGame": 30.82352,
      "seasonId": 20252026
    },
    {
      "team": "Florida Panthers",
      "abbrev": "FLA",
      "wins": 8,
      "losses": 7,
      "ot": 1,
      "points": 17,
      "gamesPlayed": 16,
      "pointPctg": 0.53125,
      "goalDifferential": -5,
      "goalsForPerGame": 2.625,
      "goalsAgainstPerGame": 2.9375,
      "shotsForPerGame": 28.125,
      "shotsAgainstPerGame": 24.6875,
      "seasonId": 20252026
    },
    {
      "team": "Vancouver Canucks",
      "abbrev": "VAN",
      "wins": 8,
      "losses": 9,
      "ot": 1,
      "points": 17,
      "gamesPlayed": 18,
      "pointPctg": 0.47222,
      "goalDifferential": -12,
      "goalsForPerGame": 2.83333,
      "goalsAgainstPerGame": 3.5,
      "shotsForPerGame": 27.55555,
      "shotsAgainstPerGame": 30.16666,
      "seasonId": 20252026
    },
    {
      "team": "St. Louis Blues",
      "abbrev": "STL",
      "wins": 6,
      "losses": 8,
      "ot": 3,
      "points": 15,
      "gamesPlayed": 17,
      "pointPctg": 0.44117,
      "goalDifferential": -17,
      "goalsForPerGame": 2.7647,
      "goalsAgainstPerGame": 3.7647,
      "shotsForPerGame": 26.23529,
      "shotsAgainstPerGame": 27.23529,
      "seasonId": 20252026
    },
    {
      "team": "Buffalo Sabres",
      "abbrev": "BUF",
      "wins": 5,
      "losses": 7,
      "ot": 4,
      "points": 14,
      "gamesPlayed": 16,
      "pointPctg": 0.4375,
      "goalDifferential": -12,
      "goalsForPerGame": 2.625,
      "goalsAgainstPerGame": 3.375,
      "shotsForPerGame": 28.3125,
      "shotsAgainstPerGame": 31.8125,
      "seasonId": 20252026
    },
    {
      "team": "Nashville Predators",
      "abbrev": "NSH",
      "wins": 5,
      "losses": 9,
      "ot": 4,
      "points": 14,
      "gamesPlayed": 18,
      "pointPctg": 0.38888,
      "goalDifferential": -19,
      "goalsForPerGame": 2.55555,
      "goalsAgainstPerGame": 3.61111,
      "shotsForPerGame": 27.16666,
      "shotsAgainstPerGame": 28.27777,
      "seasonId": 20252026
    },
    {
      "team": "Calgary Flames",
      "abbrev": "CGY",
      "wins": 4,
      "losses": 12,
      "ot": 2,
      "points": 10,
      "gamesPlayed": 18,
      "pointPctg": 0.27777,
      "goalDifferential": -20,
      "goalsForPerGame": 2.05555,
      "goalsAgainstPerGame": 3.16666,
      "shotsForPerGame": 29.27777,
      "shotsAgainstPerGame": 29.66666,
      "seasonId": 20252026
    }
  ]
}