{
  "generatedAt": "2026-01-05T14:13:58.581473Z",
  "source": "RotoWire",
  "date": "2026-01-05",
  "teams": {
    "NYR": {
      "team": "NYR",
      "playerId": 5050,
      "goalieName": "Igor Shesterkin",
      "confirmedStart": false,
      "statusCode": "expected",
      "statusDescription": "From RotoWire: Expected",
      "lastUpdated": "2026-01-05T14:13:58.892262Z"
    },
    "UTA": {
      "team": "UTA",
      "playerId": 6428,
      "goalieName": "Karel Vejmelka",
      "confirmedStart": false,
      "statusCode": "expected",
      "statusDescription": "From RotoWire: Expected",
      "lastUpdated": "2026-01-05T14:13:58.892270Z"
    },
    "WSH": {
      "team": "WSH",
      "playerId": 6355,
      "goalieName": "Logan Thompson",
      "confirmedStart": false,
      "statusCode": "expected",
      "statusDescription": "From RotoWire: Expected",
      "lastUpdated": "2026-01-05T14:13:58.892276Z"
    },
    "ANA": {
      "team": "ANA",
      "playerId": 5792,
      "goalieName": "Lukas Dostal",
      "confirmedStart": false,
      "statusCode": "expected",
      "statusDescription": "From RotoWire: Expected",
      "lastUpdated": "2026-01-05T14:13:58.892278Z"
    },
    "OTT": {
      "team": "OTT",
      "playerId": 6365,
      "goalieName": "Leevi Merilainen",
      "confirmedStart": false,
      "statusCode": "expected",
      "statusDescription": "From RotoWire: Expected",
      "lastUpdated": "2026-01-05T14:13:58.892282Z"
    },
    "DET": {
      "team": "DET",
      "playerId": 3768,
      "goalieName": "John Gibson",
      "confirmedStart": false,
      "statusCode": "expected",
      "statusDescription": "From RotoWire: Expected",
      "lastUpdated": "2026-01-05T14:13:58.892284Z"
    },
    "CGY": {
      "team": "CGY",
      "playerId": 6054,
      "goalieName": "Dustin Wolf",
      "confirmedStart": false,
      "statusCode": "expected",
      "statusDescription": "From RotoWire: Expected",
      "lastUpdated": "2026-01-05T14:13:58.892288Z"
    },
    "SEA": {
      "team": "SEA",
      "playerId": 3549,
      "goalieName": "Philipp Grubauer",
      "confirmedStart": false,
      "statusCode": "expected",
      "statusDescription": "From RotoWire: Expected",
      "lastUpdated": "2026-01-05T14:13:58.892291Z"
    },
    "LAK": {
      "team": "LAK",
      "playerId": 3739,
      "goalieName": "Darcy Kuemper",
      "confirmedStart": false,
      "statusCode": "expected",
      "statusDescription": "From RotoWire: Expected",
      "lastUpdated": "2026-01-05T14:13:58.892295Z"
    },
    "MIN": {
      "team": "MIN",
      "playerId": 5165,
      "goalieName": "Filip Gustavsson",
      "confirmedStart": false,
      "statusCode": "expected",
      "statusDescription": "From RotoWire: Expected",
      "lastUpdated": "2026-01-05T14:13:58.892297Z"
    },
    "BUF": {
      "team": "BUF",
      "playerId": null,
      "goalieName": null,
      "confirmedStart": false,
      "statusCode": "TBD",
      "statusDescription": "From NHL API: TBD",
      "lastUpdated": "2026-01-05T14:13:58.892304Z"
    },
    "VAN": {
      "team": "VAN",
      "playerId": null,
      "goalieName": null,
      "confirmedStart": false,
      "statusCode": "TBD",
      "statusDescription": "From NHL API: TBD",
      "lastUpdated": "2026-01-05T14:13:58.892318Z"
    },
    "TBL": {
      "team": "TBL",
      "playerId": null,
      "goalieName": null,
      "confirmedStart": false,
      "statusCode": "TBD",
      "statusDescription": "From NHL API: TBD",
      "lastUpdated": "2026-01-05T14:13:58.892321Z"
    },
    "COL": {
      "team": "COL",
      "playerId": null,
      "goalieName": null,
      "confirmedStart": false,
      "statusCode": "TBD",
      "statusDescription": "From NHL API: TBD",
      "lastUpdated": "2026-01-05T14:13:58.892323Z"
    },
    "PHI": {
      "team": "PHI",
      "playerId": null,
      "goalieName": null,
      "confirmedStart": false,
      "statusCode": "TBD",
      "statusDescription": "From NHL API: TBD",
      "lastUpdated": "2026-01-05T14:13:58.892325Z"
    },
    "CAR": {
      "team": "CAR",
      "playerId": null,
      "goalieName": null,
      "confirmedStart": false,
      "statusCode": "TBD",
      "statusDescription": "From NHL API: TBD",
      "lastUpdated": "2026-01-05T14:13:58.892329Z"
    },
    "DAL": {
      "team": "DAL",
      "playerId": null,
      "goalieName": null,
      "confirmedStart": false,
      "statusCode": "TBD",
      "statusDescription": "From NHL API: TBD",
      "lastUpdated": "2026-01-05T14:13:58.892330Z"
    },
    "NYI": {
      "team": "NYI",
      "playerId": null,
      "goalieName": null,
      "confirmedStart": false,
      "statusCode": "TBD",
      "statusDescription": "From NHL API: TBD",
      "lastUpdated": "2026-01-05T14:13:58.892332Z"
    },
    "NJD": {
      "team": "NJD",
      "playerId": null,
      "goalieName": null,
      "confirmedStart": false,
      "statusCode": "TBD",
      "statusDescription": "From NHL API: TBD",
      "lastUpdated": "2026-01-05T14:13:58.892333Z"
    },
    "TOR": {
      "team": "TOR",
      "playerId": null,
      "goalieName": null,
      "confirmedStart": false,
      "statusCode": "TBD",
      "statusDescription": "From NHL API: TBD",
      "lastUpdated": "2026-01-05T14:13:58.892336Z"
    },
    "FLA": {
      "team": "FLA",
      "playerId": null,
      "goalieName": null,
      "confirmedStart": false,
      "statusCode": "TBD",
      "statusDescription": "From NHL API: TBD",
      "lastUpdated": "2026-01-05T14:13:58.892337Z"
    },
    "WPG": {
      "team": "WPG",
      "playerId": null,
      "goalieName": null,
      "confirmedStart": false,
      "statusCode": "TBD",
      "statusDescription": "From NHL API: TBD",
      "lastUpdated": "2026-01-05T14:13:58.892339Z"
    },
    "VGK": {
      "team": "VGK",
      "playerId": null,
      "goalieName": null,
      "confirmedStart": false,
      "statusCode": "TBD",
      "statusDescription": "From NHL API: TBD",
      "lastUpdated": "2026-01-05T14:13:58.892340Z"
    },
    "EDM": {
      "team": "EDM",
      "playerId": null,
      "goalieName": null,
      "confirmedStart": false,
      "statusCode": "TBD",
      "statusDescription": "From NHL API: TBD",
      "lastUpdated": "2026-01-05T14:13:58.892343Z"
    },
    "NSH": {
      "team": "NSH",
      "playerId": null,
      "goalieName": null,
      "confirmedStart": false,
      "statusCode": "TBD",
      "statusDescription": "From NHL API: TBD",
      "lastUpdated": "2026-01-05T14:13:58.892344Z"
    },
    "SJS": {
      "team": "SJS",
      "playerId": null,
      "goalieName": null,
      "confirmedStart": false,
      "statusCode": "TBD",
      "statusDescription": "From NHL API: TBD",
      "lastUpdated": "2026-01-05T14:13:58.892346Z"
    },
    "CBJ": {
      "team": "CBJ",
      "playerId": null,
      "goalieName": null,
      "confirmedStart": false,
      "statusCode": "TBD",
      "statusDescription": "From NHL API: TBD",
      "lastUpdated": "2026-01-05T14:13:58.892347Z"
    },
    "BOS": {
      "team": "BOS",
      "playerId": null,
      "goalieName": null,
      "confirmedStart": false,
      "statusCode": "TBD",
      "statusDescription": "From NHL API: TBD",
      "lastUpdated": "2026-01-05T14:13:58.892350Z"
    },
    "MTL": {
      "team": "MTL",
      "playerId": null,
      "goalieName": null,
      "confirmedStart": false,
      "statusCode": "TBD",
      "statusDescription": "From NHL API: TBD",
      "lastUpdated": "2026-01-05T14:13:58.892356Z"
    },
    "CHI": {
      "team": "CHI",
      "playerId": null,
      "goalieName": null,
      "confirmedStart": false,
      "statusCode": "TBD",
      "statusDescription": "From NHL API: TBD",
      "lastUpdated": "2026-01-05T14:13:58.892359Z"
    },
    "STL": {
      "team": "STL",
      "playerId": null,
      "goalieName": null,
      "confirmedStart": false,
      "statusCode": "TBD",
      "statusDescription": "From NHL API: TBD",
      "lastUpdated": "2026-01-05T14:13:58.892360Z"
    },
    "PIT": {
      "team": "PIT",
      "playerId": null,
      "goalieName": null,
      "confirmedStart": false,
      "statusCode": "TBD",
      "statusDescription": "From NHL API: TBD",
      "lastUpdated": "2026-01-05T14:13:58.892388Z"
    }
  },
  "games": [
    {
      "gameId": "2025020662",
      "gameDate": "2026-01-05",
      "startTimeUTC": "2026-01-06T00:00:00Z",
      "startTimeET": "7:00 PM",
      "homeTeam": "NYR",
      "awayTeam": "UTA",
      "homeGoalie": {
        "team": "NYR",
        "playerId": 5050,
        "goalieName": "Igor Shesterkin",
        "confirmedStart": false,
        "statusCode": "expected",
        "statusDescription": "From RotoWire: Expected",
        "lastUpdated": "2026-01-05T14:13:58.892262Z"
      },
      "awayGoalie": {
        "team": "UTA",
        "playerId": 6428,
        "goalieName": "Karel Vejmelka",
        "confirmedStart": false,
        "statusCode": "expected",
        "statusDescription": "From RotoWire: Expected",
        "lastUpdated": "2026-01-05T14:13:58.892270Z"
      }
    },
    {
      "gameId": "2025020663",
      "gameDate": "2026-01-05",
      "startTimeUTC": "2026-01-06T00:00:00Z",
      "startTimeET": "7:00 PM",
      "homeTeam": "WSH",
      "awayTeam": "ANA",
      "homeGoalie": {
        "team": "WSH",
        "playerId": 6355,
        "goalieName": "Logan Thompson",
        "confirmedStart": false,
        "statusCode": "expected",
        "statusDescription": "From RotoWire: Expected",
        "lastUpdated": "2026-01-05T14:13:58.892276Z"
      },
      "awayGoalie": {
        "team": "ANA",
        "playerId": 5792,
        "goalieName": "Lukas Dostal",
        "confirmedStart": false,
        "statusCode": "expected",
        "statusDescription": "From RotoWire: Expected",
        "lastUpdated": "2026-01-05T14:13:58.892278Z"
      }
    },
    {
      "gameId": "2025020664",
      "gameDate": "2026-01-05",
      "startTimeUTC": "2026-01-06T00:30:00Z",
      "startTimeET": "7:30 PM",
      "homeTeam": "OTT",
      "awayTeam": "DET",
      "homeGoalie": {
        "team": "OTT",
        "playerId": 6365,
        "goalieName": "Leevi Merilainen",
        "confirmedStart": false,
        "statusCode": "expected",
        "statusDescription": "From RotoWire: Expected",
        "lastUpdated": "2026-01-05T14:13:58.892282Z"
      },
      "awayGoalie": {
        "team": "DET",
        "playerId": 3768,
        "goalieName": "John Gibson",
        "confirmedStart": false,
        "statusCode": "expected",
        "statusDescription": "From RotoWire: Expected",
        "lastUpdated": "2026-01-05T14:13:58.892284Z"
      }
    },
    {
      "gameId": "2025020665",
      "gameDate": "2026-01-05",
      "startTimeUTC": "2026-01-06T02:30:00Z",
      "startTimeET": "9:30 PM",
      "homeTeam": "CGY",
      "awayTeam": "SEA",
      "homeGoalie": {
        "team": "CGY",
        "playerId": 6054,
        "goalieName": "Dustin Wolf",
        "confirmedStart": false,
        "statusCode": "expected",
        "statusDescription": "From RotoWire: Expected",
        "lastUpdated": "2026-01-05T14:13:58.892288Z"
      },
      "awayGoalie": {
        "team": "SEA",
        "playerId": 3549,
        "goalieName": "Philipp Grubauer",
        "confirmedStart": false,
        "statusCode": "expected",
        "statusDescription": "From RotoWire: Expected",
        "lastUpdated": "2026-01-05T14:13:58.892291Z"
      }
    },
    {
      "gameId": "2025020666",
      "gameDate": "2026-01-05",
      "startTimeUTC": "2026-01-06T03:30:00Z",
      "startTimeET": "10:30 PM",
      "homeTeam": "LAK",
      "awayTeam": "MIN",
      "homeGoalie": {
        "team": "LAK",
        "playerId": 3739,
        "goalieName": "Darcy Kuemper",
        "confirmedStart": false,
        "statusCode": "expected",
        "statusDescription": "From RotoWire: Expected",
        "lastUpdated": "2026-01-05T14:13:58.892295Z"
      },
      "awayGoalie": {
        "team": "MIN",
        "playerId": 5165,
        "goalieName": "Filip Gustavsson",
        "confirmedStart": false,
        "statusCode": "expected",
        "statusDescription": "From RotoWire: Expected",
        "lastUpdated": "2026-01-05T14:13:58.892297Z"
      }
    },
    {
      "gameId": "2025020667",
      "gameDate": "2026-01-06",
      "startTimeUTC": "2026-01-07T00:00:00Z",
      "homeTeam": "BUF",
      "awayTeam": "VAN",
      "homeGoalie": {
        "team": "BUF",
        "playerId": null,
        "goalieName": null,
        "confirmedStart": false,
        "statusCode": "TBD",
        "statusDescription": "From NHL API: TBD",
        "lastUpdated": "2026-01-05T14:13:58.892304Z"
      },
      "awayGoalie": {
        "team": "VAN",
        "playerId": null,
        "goalieName": null,
        "confirmedStart": false,
        "statusCode": "TBD",
        "statusDescription": "From NHL API: TBD",
        "lastUpdated": "2026-01-05T14:13:58.892318Z"
      }
    },
    {
      "gameId": "2025020668",
      "gameDate": "2026-01-06",
      "startTimeUTC": "2026-01-07T00:00:00Z",
      "homeTeam": "TBL",
      "awayTeam": "COL",
      "homeGoalie": {
        "team": "TBL",
        "playerId": null,
        "goalieName": null,
        "confirmedStart": false,
        "statusCode": "TBD",
        "statusDescription": "From NHL API: TBD",
        "lastUpdated": "2026-01-05T14:13:58.892321Z"
      },
      "awayGoalie": {
        "team": "COL",
        "playerId": null,
        "goalieName": null,
        "confirmedStart": false,
        "statusCode": "TBD",
        "statusDescription": "From NHL API: TBD",
        "lastUpdated": "2026-01-05T14:13:58.892323Z"
      }
    },
    {
      "gameId": "2025020670",
      "gameDate": "2026-01-06",
      "startTimeUTC": "2026-01-07T00:00:00Z",
      "homeTeam": "PHI",
      "awayTeam": "ANA",
      "homeGoalie": {
        "team": "PHI",
        "playerId": null,
        "goalieName": null,
        "confirmedStart": false,
        "statusCode": "TBD",
        "statusDescription": "From NHL API: TBD",
        "lastUpdated": "2026-01-05T14:13:58.892325Z"
      },
      "awayGoalie": {
        "team": "ANA",
        "playerId": null,
        "goalieName": null,
        "confirmedStart": false,
        "statusCode": "TBD",
        "statusDescription": "From NHL API: TBD",
        "lastUpdated": "2026-01-05T14:13:58.892326Z"
      }
    },
    {
      "gameId": "2025020671",
      "gameDate": "2026-01-06",
      "startTimeUTC": "2026-01-07T00:00:00Z",
      "homeTeam": "CAR",
      "awayTeam": "DAL",
      "homeGoalie": {
        "team": "CAR",
        "playerId": null,
        "goalieName": null,
        "confirmedStart": false,
        "statusCode": "TBD",
        "statusDescription": "From NHL API: TBD",
        "lastUpdated": "2026-01-05T14:13:58.892329Z"
      },
      "awayGoalie": {
        "team": "DAL",
        "playerId": null,
        "goalieName": null,
        "confirmedStart": false,
        "statusCode": "TBD",
        "statusDescription": "From NHL API: TBD",
        "lastUpdated": "2026-01-05T14:13:58.892330Z"
      }
    },
    {
      "gameId": "2025020669",
      "gameDate": "2026-01-06",
      "startTimeUTC": "2026-01-07T00:30:00Z",
      "homeTeam": "NYI",
      "awayTeam": "NJD",
      "homeGoalie": {
        "team": "NYI",
        "playerId": null,
        "goalieName": null,
        "confirmedStart": false,
        "statusCode": "TBD",
        "statusDescription": "From NHL API: TBD",
        "lastUpdated": "2026-01-05T14:13:58.892332Z"
      },
      "awayGoalie": {
        "team": "NJD",
        "playerId": null,
        "goalieName": null,
        "confirmedStart": false,
        "statusCode": "TBD",
        "statusDescription": "From NHL API: TBD",
        "lastUpdated": "2026-01-05T14:13:58.892333Z"
      }
    },
    {
      "gameId": "2025020672",
      "gameDate": "2026-01-06",
      "startTimeUTC": "2026-01-07T00:30:00Z",
      "homeTeam": "TOR",
      "awayTeam": "FLA",
      "homeGoalie": {
        "team": "TOR",
        "playerId": null,
        "goalieName": null,
        "confirmedStart": false,
        "statusCode": "TBD",
        "statusDescription": "From NHL API: TBD",
        "lastUpdated": "2026-01-05T14:13:58.892336Z"
      },
      "awayGoalie": {
        "team": "FLA",
        "playerId": null,
        "goalieName": null,
        "confirmedStart": false,
        "statusCode": "TBD",
        "statusDescription": "From NHL API: TBD",
        "lastUpdated": "2026-01-05T14:13:58.892337Z"
      }
    },
    {
      "gameId": "2025020673",
      "gameDate": "2026-01-06",
      "startTimeUTC": "2026-01-07T01:00:00Z",
      "homeTeam": "WPG",
      "awayTeam": "VGK",
      "homeGoalie": {
        "team": "WPG",
        "playerId": null,
        "goalieName": null,
        "confirmedStart": false,
        "statusCode": "TBD",
        "statusDescription": "From NHL API: TBD",
        "lastUpdated": "2026-01-05T14:13:58.892339Z"
      },
      "awayGoalie": {
        "team": "VGK",
        "playerId": null,
        "goalieName": null,
        "confirmedStart": false,
        "statusCode": "TBD",
        "statusDescription": "From NHL API: TBD",
        "lastUpdated": "2026-01-05T14:13:58.892340Z"
      }
    },
    {
      "gameId": "2025020674",
      "gameDate": "2026-01-06",
      "startTimeUTC": "2026-01-07T02:00:00Z",
      "homeTeam": "EDM",
      "awayTeam": "NSH",
      "homeGoalie": {
        "team": "EDM",
        "playerId": null,
        "goalieName": null,
        "confirmedStart": false,
        "statusCode": "TBD",
        "statusDescription": "From NHL API: TBD",
        "lastUpdated": "2026-01-05T14:13:58.892343Z"
      },
      "awayGoalie": {
        "team": "NSH",
        "playerId": null,
        "goalieName": null,
        "confirmedStart": false,
        "statusCode": "TBD",
        "statusDescription": "From NHL API: TBD",
        "lastUpdated": "2026-01-05T14:13:58.892344Z"
      }
    },
    {
      "gameId": "2025020675",
      "gameDate": "2026-01-06",
      "startTimeUTC": "2026-01-07T03:00:00Z",
      "homeTeam": "SJS",
      "awayTeam": "CBJ",
      "homeGoalie": {
        "team": "SJS",
        "playerId": null,
        "goalieName": null,
        "confirmedStart": false,
        "statusCode": "TBD",
        "statusDescription": "From NHL API: TBD",
        "lastUpdated": "2026-01-05T14:13:58.892346Z"
      },
      "awayGoalie": {
        "team": "CBJ",
        "playerId": null,
        "goalieName": null,
        "confirmedStart": false,
        "statusCode": "TBD",
        "statusDescription": "From NHL API: TBD",
        "lastUpdated": "2026-01-05T14:13:58.892347Z"
      }
    },
    {
      "gameId": "2025020676",
      "gameDate": "2026-01-06",
      "startTimeUTC": "2026-01-07T03:00:00Z",
      "homeTeam": "SEA",
      "awayTeam": "BOS",
      "homeGoalie": {
        "team": "SEA",
        "playerId": null,
        "goalieName": null,
        "confirmedStart": false,
        "statusCode": "TBD",
        "statusDescription": "From NHL API: TBD",
        "lastUpdated": "2026-01-05T14:13:58.892349Z"
      },
      "awayGoalie": {
        "team": "BOS",
        "playerId": null,
        "goalieName": null,
        "confirmedStart": false,
        "statusCode": "TBD",
        "statusDescription": "From NHL API: TBD",
        "lastUpdated": "2026-01-05T14:13:58.892350Z"
      }
    },
    {
      "gameId": "2025020677",
      "gameDate": "2026-01-07",
      "startTimeUTC": "2026-01-08T00:00:00Z",
      "homeTeam": "WSH",
      "awayTeam": "DAL",
      "homeGoalie": {
        "team": "WSH",
        "playerId": null,
        "goalieName": null,
        "confirmedStart": false,
        "statusCode": "TBD",
        "statusDescription": "From NHL API: TBD",
        "lastUpdated": "2026-01-05T14:13:58.892352Z"
      },
      "awayGoalie": {
        "team": "DAL",
        "playerId": null,
        "goalieName": null,
        "confirmedStart": false,
        "statusCode": "TBD",
        "statusDescription": "From NHL API: TBD",
        "lastUpdated": "2026-01-05T14:13:58.892354Z"
      }
    },
    {
      "gameId": "2025020678",
      "gameDate": "2026-01-07",
      "startTimeUTC": "2026-01-08T00:30:00Z",
      "homeTeam": "MTL",
      "awayTeam": "CGY",
      "homeGoalie": {
        "team": "MTL",
        "playerId": null,
        "goalieName": null,
        "confirmedStart": false,
        "statusCode": "TBD",
        "statusDescription": "From NHL API: TBD",
        "lastUpdated": "2026-01-05T14:13:58.892356Z"
      },
      "awayGoalie": {
        "team": "CGY",
        "playerId": null,
        "goalieName": null,
        "confirmedStart": false,
        "statusCode": "TBD",
        "statusDescription": "From NHL API: TBD",
        "lastUpdated": "2026-01-05T14:13:58.892357Z"
      }
    },
    {
      "gameId": "2025020679",
      "gameDate": "2026-01-07",
      "startTimeUTC": "2026-01-08T02:30:00Z",
      "homeTeam": "CHI",
      "awayTeam": "STL",
      "homeGoalie": {
        "team": "CHI",
        "playerId": null,
        "goalieName": null,
        "confirmedStart": false,
        "statusCode": "TBD",
        "statusDescription": "From NHL API: TBD",
        "lastUpdated": "2026-01-05T14:13:58.892359Z"
      },
      "awayGoalie": {
        "team": "STL",
        "playerId": null,
        "goalieName": null,
        "confirmedStart": false,
        "statusCode": "TBD",
        "statusDescription": "From NHL API: TBD",
        "lastUpdated": "2026-01-05T14:13:58.892360Z"
      }
    },
    {
      "gameId": "2025020680",
      "gameDate": "2026-01-07",
      "startTimeUTC": "2026-01-08T02:30:00Z",
      "homeTeam": "UTA",
      "awayTeam": "OTT",
      "homeGoalie": {
        "team": "UTA",
        "playerId": null,
        "goalieName": null,
        "confirmedStart": false,
        "statusCode": "TBD",
        "statusDescription": "From NHL API: TBD",
        "lastUpdated": "2026-01-05T14:13:58.892362Z"
      },
      "awayGoalie": {
        "team": "OTT",
        "playerId": null,
        "goalieName": null,
        "confirmedStart": false,
        "statusCode": "TBD",
        "statusDescription": "From NHL API: TBD",
        "lastUpdated": "2026-01-05T14:13:58.892364Z"
      }
    },
    {
      "gameId": "2025020681",
      "gameDate": "2026-01-07",
      "startTimeUTC": "2026-01-08T03:30:00Z",
      "homeTeam": "LAK",
      "awayTeam": "SJS",
      "homeGoalie": {
        "team": "LAK",
        "playerId": null,
        "goalieName": null,
        "confirmedStart": false,
        "statusCode": "TBD",
        "statusDescription": "From NHL API: TBD",
        "lastUpdated": "2026-01-05T14:13:58.892365Z"
      },
      "awayGoalie": {
        "team": "SJS",
        "playerId": null,
        "goalieName": null,
        "confirmedStart": false,
        "statusCode": "TBD",
        "statusDescription": "From NHL API: TBD",
        "lastUpdated": "2026-01-05T14:13:58.892367Z"
      }
    },
    {
      "gameId": "2025020682",
      "gameDate": "2026-01-08",
      "startTimeUTC": "2026-01-09T00:00:00Z",
      "homeTeam": "BOS",
      "awayTeam": "CGY",
      "homeGoalie": {
        "team": "BOS",
        "playerId": null,
        "goalieName": null,
        "confirmedStart": false,
        "statusCode": "TBD",
        "statusDescription": "From NHL API: TBD",
        "lastUpdated": "2026-01-05T14:13:58.892368Z"
      },
      "awayGoalie": {
        "team": "CGY",
        "playerId": null,
        "goalieName": null,
        "confirmedStart": false,
        "statusCode": "TBD",
        "statusDescription": "From NHL API: TBD",
        "lastUpdated": "2026-01-05T14:13:58.892370Z"
      }
    },
    {
      "gameId": "2025020683",
      "gameDate": "2026-01-08",
      "startTimeUTC": "2026-01-09T00:00:00Z",
      "homeTeam": "MTL",
      "awayTeam": "FLA",
      "homeGoalie": {
        "team": "MTL",
        "playerId": null,
        "goalieName": null,
        "confirmedStart": false,
        "statusCode": "TBD",
        "statusDescription": "From NHL API: TBD",
        "lastUpdated": "2026-01-05T14:13:58.892372Z"
      },
      "awayGoalie": {
        "team": "FLA",
        "playerId": null,
        "goalieName": null,
        "confirmedStart": false,
        "statusCode": "TBD",
        "statusDescription": "From NHL API: TBD",
        "lastUpdated": "2026-01-05T14:13:58.892373Z"
      }
    },
    {
      "gameId": "2025020684",
      "gameDate": "2026-01-08",
      "startTimeUTC": "2026-01-09T00:00:00Z",
      "homeTeam": "DET",
      "awayTeam": "VAN",
      "homeGoalie": {
        "team": "DET",
        "playerId": null,
        "goalieName": null,
        "confirmedStart": false,
        "statusCode": "TBD",
        "statusDescription": "From NHL API: TBD",
        "lastUpdated": "2026-01-05T14:13:58.892375Z"
      },
      "awayGoalie": {
        "team": "VAN",
        "playerId": null,
        "goalieName": null,
        "confirmedStart": false,
        "statusCode": "TBD",
        "statusDescription": "From NHL API: TBD",
        "lastUpdated": "2026-01-05T14:13:58.892376Z"
      }
    },
    {
      "gameId": "2025020685",
      "gameDate": "2026-01-08",
      "startTimeUTC": "2026-01-09T00:00:00Z",
      "homeTeam": "NYR",
      "awayTeam": "BUF",
      "homeGoalie": {
        "team": "NYR",
        "playerId": null,
        "goalieName": null,
        "confirmedStart": false,
        "statusCode": "TBD",
        "statusDescription": "From NHL API: TBD",
        "lastUpdated": "2026-01-05T14:13:58.892378Z"
      },
      "awayGoalie": {
        "team": "BUF",
        "playerId": null,
        "goalieName": null,
        "confirmedStart": false,
        "statusCode": "TBD",
        "statusDescription": "From NHL API: TBD",
        "lastUpdated": "2026-01-05T14:13:58.892383Z"
      }
    },
    {
      "gameId": "2025020686",
      "gameDate": "2026-01-08",
      "startTimeUTC": "2026-01-09T00:00:00Z",
      "homeTeam": "PHI",
      "awayTeam": "TOR",
      "homeGoalie": {
        "team": "PHI",
        "playerId": null,
        "goalieName": null,
        "confirmedStart": false,
        "statusCode": "TBD",
        "statusDescription": "From NHL API: TBD",
        "lastUpdated": "2026-01-05T14:13:58.892384Z"
      },
      "awayGoalie": {
        "team": "TOR",
        "playerId": null,
        "goalieName": null,
        "confirmedStart": false,
        "statusCode": "TBD",
        "statusDescription": "From NHL API: TBD",
        "lastUpdated": "2026-01-05T14:13:58.892386Z"
      }
    },
    {
      "gameId": "2025020687",
      "gameDate": "2026-01-08",
      "startTimeUTC": "2026-01-09T00:00:00Z",
      "homeTeam": "PIT",
      "awayTeam": "NJD",
      "homeGoalie": {
        "team": "PIT",
        "playerId": null,
        "goalieName": null,
        "confirmedStart": false,
        "statusCode": "TBD",
        "statusDescription": "From NHL API: TBD",
        "lastUpdated": "2026-01-05T14:13:58.892388Z"
      },
      "awayGoalie": {
        "team": "NJD",
        "playerId": null,
        "goalieName": null,
        "confirmedStart": false,
        "statusCode": "TBD",
        "statusDescription": "From NHL API: TBD",
        "lastUpdated": "2026-01-05T14:13:58.892389Z"
      }
    },
    {
      "gameId": "2025020688",
      "gameDate": "2026-01-08",
      "startTimeUTC": "2026-01-09T00:00:00Z",
      "homeTeam": "CAR",
      "awayTeam": "ANA",
      "homeGoalie": {
        "team": "CAR",
        "playerId": null,
        "goalieName": null,
        "confirmedStart": false,
        "statusCode": "TBD",
        "statusDescription": "From NHL API: TBD",
        "lastUpdated": "2026-01-05T14:13:58.892391Z"
      },
      "awayGoalie": {
        "team": "ANA",
        "playerId": null,
        "goalieName": null,
        "confirmedStart": false,
        "statusCode": "TBD",
        "statusDescription": "From NHL API: TBD",
        "lastUpdated": "2026-01-05T14:13:58.892392Z"
      }
    },
    {
      "gameId": "2025020689",
      "gameDate": "2026-01-08",
      "startTimeUTC": "2026-01-09T01:00:00Z",
      "homeTeam": "NSH",
      "awayTeam": "NYI",
      "homeGoalie": {
        "team": "NSH",
        "playerId": null,
        "goalieName": null,
        "confirmedStart": false,
        "statusCode": "TBD",
        "statusDescription": "From NHL API: TBD",
        "lastUpdated": "2026-01-05T14:13:58.892394Z"
      },
      "awayGoalie": {
        "team": "NYI",
        "playerId": null,
        "goalieName": null,
        "confirmedStart": false,
        "statusCode": "TBD",
        "statusDescription": "From NHL API: TBD",
        "lastUpdated": "2026-01-05T14:13:58.892395Z"
      }
    },
    {
      "gameId": "2025020690",
      "gameDate": "2026-01-08",
      "startTimeUTC": "2026-01-09T01:00:00Z",
      "homeTeam": "WPG",
      "awayTeam": "EDM",
      "homeGoalie": {
        "team": "WPG",
        "playerId": null,
        "goalieName": null,
        "confirmedStart": false,
        "statusCode": "TBD",
        "statusDescription": "From NHL API: TBD",
        "lastUpdated": "2026-01-05T14:13:58.892397Z"
      },
      "awayGoalie": {
        "team": "EDM",
        "playerId": null,
        "goalieName": null,
        "confirmedStart": false,
        "statusCode": "TBD",
        "statusDescription": "From NHL API: TBD",
        "lastUpdated": "2026-01-05T14:13:58.892398Z"
      }
    },
    {
      "gameId": "2025020691",
      "gameDate": "2026-01-08",
      "startTimeUTC": "2026-01-09T02:00:00Z",
      "homeTeam": "COL",
      "awayTeam": "OTT",
      "homeGoalie": {
        "team": "COL",
        "playerId": null,
        "goalieName": null,
        "confirmedStart": false,
        "statusCode": "TBD",
        "statusDescription": "From NHL API: TBD",
        "lastUpdated": "2026-01-05T14:13:58.892400Z"
      },
      "awayGoalie": {
        "team": "OTT",
        "playerId": null,
        "goalieName": null,
        "confirmedStart": false,
        "statusCode": "TBD",
        "statusDescription": "From NHL API: TBD",
        "lastUpdated": "2026-01-05T14:13:58.892402Z"
      }
    },
    {
      "gameId": "2025020692",
      "gameDate": "2026-01-08",
      "startTimeUTC": "2026-01-09T03:00:00Z",
      "homeTeam": "VGK",
      "awayTeam": "CBJ",
      "homeGoalie": {
        "team": "VGK",
        "playerId": null,
        "goalieName": null,
        "confirmedStart": false,
        "statusCode": "TBD",
        "statusDescription": "From NHL API: TBD",
        "lastUpdated": "2026-01-05T14:13:58.892403Z"
      },
      "awayGoalie": {
        "team": "CBJ",
        "playerId": null,
        "goalieName": null,
        "confirmedStart": false,
        "statusCode": "TBD",
        "statusDescription": "From NHL API: TBD",
        "lastUpdated": "2026-01-05T14:13:58.892405Z"
      }
    },
    {
      "gameId": "2025020693",
      "gameDate": "2026-01-08",
      "startTimeUTC": "2026-01-09T03:00:00Z",
      "homeTeam": "SEA",
      "awayTeam": "MIN",
      "homeGoalie": {
        "team": "SEA",
        "playerId": null,
        "goalieName": null,
        "confirmedStart": false,
        "statusCode": "TBD",
        "statusDescription": "From NHL API: TBD",
        "lastUpdated": "2026-01-05T14:13:58.892407Z"
      },
      "awayGoalie": {
        "team": "MIN",
        "playerId": null,
        "goalieName": null,
        "confirmedStart": false,
        "statusCode": "TBD",
        "statusDescription": "From NHL API: TBD",
        "lastUpdated": "2026-01-05T14:13:58.892408Z"
      }
    },
    {
      "gameId": "2025020694",
      "gameDate": "2026-01-09",
      "startTimeUTC": "2026-01-10T01:00:00Z",
      "homeTeam": "CHI",
      "awayTeam": "WSH",
      "homeGoalie": {
        "team": "CHI",
        "playerId": null,
        "goalieName": null,
        "confirmedStart": false,
        "statusCode": "TBD",
        "statusDescription": "From NHL API: TBD",
        "lastUpdated": "2026-01-05T14:13:58.892410Z"
      },
      "awayGoalie": {
        "team": "WSH",
        "playerId": null,
        "goalieName": null,
        "confirmedStart": false,
        "statusCode": "TBD",
        "statusDescription": "From NHL API: TBD",
        "lastUpdated": "2026-01-05T14:13:58.892411Z"
      }
    },
    {
      "gameId": "2025020695",
      "gameDate": "2026-01-09",
      "startTimeUTC": "2026-01-10T01:00:00Z",
      "homeTeam": "WPG",
      "awayTeam": "LAK",
      "homeGoalie": {
        "team": "WPG",
        "playerId": null,
        "goalieName": null,
        "confirmedStart": false,
        "statusCode": "TBD",
        "statusDescription": "From NHL API: TBD",
        "lastUpdated": "2026-01-05T14:13:58.892413Z"
      },
      "awayGoalie": {
        "team": "LAK",
        "playerId": null,
        "goalieName": null,
        "confirmedStart": false,
        "statusCode": "TBD",
        "statusDescription": "From NHL API: TBD",
        "lastUpdated": "2026-01-05T14:13:58.892414Z"
      }
    },
    {
      "gameId": "2025020696",
      "gameDate": "2026-01-09",
      "startTimeUTC": "2026-01-10T02:00:00Z",
      "homeTeam": "UTA",
      "awayTeam": "STL",
      "homeGoalie": {
        "team": "UTA",
        "playerId": null,
        "goalieName": null,
        "confirmedStart": false,
        "statusCode": "TBD",
        "statusDescription": "From NHL API: TBD",
        "lastUpdated": "2026-01-05T14:13:58.892416Z"
      },
      "awayGoalie": {
        "team": "STL",
        "playerId": null,
        "goalieName": null,
        "confirmedStart": false,
        "statusCode": "TBD",
        "statusDescription": "From NHL API: TBD",
        "lastUpdated": "2026-01-05T14:13:58.892418Z"
      }
    },
    {
      "gameId": "2025020697",
      "gameDate": "2026-01-10",
      "startTimeUTC": "2026-01-10T18:00:00Z",
      "homeTeam": "BOS",
      "awayTeam": "NYR",
      "homeGoalie": {
        "team": "BOS",
        "playerId": null,
        "goalieName": null,
        "confirmedStart": false,
        "statusCode": "TBD",
        "statusDescription": "From NHL API: TBD",
        "lastUpdated": "2026-01-05T14:13:58.892419Z"
      },
      "awayGoalie": {
        "team": "NYR",
        "playerId": null,
        "goalieName": null,
        "confirmedStart": false,
        "statusCode": "TBD",
        "statusDescription": "From NHL API: TBD",
        "lastUpdated": "2026-01-05T14:13:58.892421Z"
      }
    },
    {
      "gameId": "2025020698",
      "gameDate": "2026-01-10",
      "startTimeUTC": "2026-01-10T20:30:00Z",
      "homeTeam": "PIT",
      "awayTeam": "CGY",
      "homeGoalie": {
        "team": "PIT",
        "playerId": null,
        "goalieName": null,
        "confirmedStart": false,
        "statusCode": "TBD",
        "statusDescription": "From NHL API: TBD",
        "lastUpdated": "2026-01-05T14:13:58.892424Z"
      },
      "awayGoalie": {
        "team": "CGY",
        "playerId": null,
        "goalieName": null,
        "confirmedStart": false,
        "statusCode": "TBD",
        "statusDescription": "From NHL API: TBD",
        "lastUpdated": "2026-01-05T14:13:58.892426Z"
      }
    },
    {
      "gameId": "2025020699",
      "gameDate": "2026-01-10",
      "startTimeUTC": "2026-01-10T21:00:00Z",
      "homeTeam": "COL",
      "awayTeam": "CBJ",
      "homeGoalie": {
        "team": "COL",
        "playerId": null,
        "goalieName": null,
        "confirmedStart": false,
        "statusCode": "TBD",
        "statusDescription": "From NHL API: TBD",
        "lastUpdated": "2026-01-05T14:13:58.892428Z"
      },
      "awayGoalie": {
        "team": "CBJ",
        "playerId": null,
        "goalieName": null,
        "confirmedStart": false,
        "statusCode": "TBD",
        "statusDescription": "From NHL API: TBD",
        "lastUpdated": "2026-01-05T14:13:58.892429Z"
      }
    },
    {
      "gameId": "2025020700",
      "gameDate": "2026-01-10",
      "startTimeUTC": "2026-01-10T21:00:00Z",
      "homeTeam": "SJS",
      "awayTeam": "DAL",
      "homeGoalie": {
        "team": "SJS",
        "playerId": null,
        "goalieName": null,
        "confirmedStart": false,
        "statusCode": "TBD",
        "statusDescription": "From NHL API: TBD",
        "lastUpdated": "2026-01-05T14:13:58.892431Z"
      },
      "awayGoalie": {
        "team": "DAL",
        "playerId": null,
        "goalieName": null,
        "confirmedStart": false,
        "statusCode": "TBD",
        "statusDescription": "From NHL API: TBD",
        "lastUpdated": "2026-01-05T14:13:58.892432Z"
      }
    },
    {
      "gameId": "2025020701",
      "gameDate": "2026-01-10",
      "startTimeUTC": "2026-01-11T00:00:00Z",
      "homeTeam": "BUF",
      "awayTeam": "ANA",
      "homeGoalie": {
        "team": "BUF",
        "playerId": null,
        "goalieName": null,
        "confirmedStart": false,
        "statusCode": "TBD",
        "statusDescription": "From NHL API: TBD",
        "lastUpdated": "2026-01-05T14:13:58.892434Z"
      },
      "awayGoalie": {
        "team": "ANA",
        "playerId": null,
        "goalieName": null,
        "confirmedStart": false,
        "statusCode": "TBD",
        "statusDescription": "From NHL API: TBD",
        "lastUpdated": "2026-01-05T14:13:58.892435Z"
      }
    },
    {
      "gameId": "2025020702",
      "gameDate": "2026-01-10",
      "startTimeUTC": "2026-01-11T00:00:00Z",
      "homeTeam": "TOR",
      "awayTeam": "VAN",
      "homeGoalie": {
        "team": "TOR",
        "playerId": null,
        "goalieName": null,
        "confirmedStart": false,
        "statusCode": "TBD",
        "statusDescription": "From NHL API: TBD",
        "lastUpdated": "2026-01-05T14:13:58.892437Z"
      },
      "awayGoalie": {
        "team": "VAN",
        "playerId": null,
        "goalieName": null,
        "confirmedStart": false,
        "statusCode": "TBD",
        "statusDescription": "From NHL API: TBD",
        "lastUpdated": "2026-01-05T14:13:58.892438Z"
      }
    },
    {
      "gameId": "2025020703",
      "gameDate": "2026-01-10",
      "startTimeUTC": "2026-01-11T00:00:00Z",
      "homeTeam": "MTL",
      "awayTeam": "DET",
      "homeGoalie": {
        "team": "MTL",
        "playerId": null,
        "goalieName": null,
        "confirmedStart": false,
        "statusCode": "TBD",
        "statusDescription": "From NHL API: TBD",
        "lastUpdated": "2026-01-05T14:13:58.892440Z"
      },
      "awayGoalie": {
        "team": "DET",
        "playerId": null,
        "goalieName": null,
        "confirmedStart": false,
        "statusCode": "TBD",
        "statusDescription": "From NHL API: TBD",
        "lastUpdated": "2026-01-05T14:13:58.892441Z"
      }
    },
    {
      "gameId": "2025020704",
      "gameDate": "2026-01-10",
      "startTimeUTC": "2026-01-11T00:00:00Z",
      "homeTeam": "OTT",
      "awayTeam": "FLA",
      "homeGoalie": {
        "team": "OTT",
        "playerId": null,
        "goalieName": null,
        "confirmedStart": false,
        "statusCode": "TBD",
        "statusDescription": "From NHL API: TBD",
        "lastUpdated": "2026-01-05T14:13:58.892443Z"
      },
      "awayGoalie": {
        "team": "FLA",
        "playerId": null,
        "goalieName": null,
        "confirmedStart": false,
        "statusCode": "TBD",
        "statusDescription": "From NHL API: TBD",
        "lastUpdated": "2026-01-05T14:13:58.892445Z"
      }
    },
    {
      "gameId": "2025020705",
      "gameDate": "2026-01-10",
      "startTimeUTC": "2026-01-11T00:00:00Z",
      "homeTeam": "PHI",
      "awayTeam": "TBL",
      "homeGoalie": {
        "team": "PHI",
        "playerId": null,
        "goalieName": null,
        "confirmedStart": false,
        "statusCode": "TBD",
        "statusDescription": "From NHL API: TBD",
        "lastUpdated": "2026-01-05T14:13:58.892446Z"
      },
      "awayGoalie": {
        "team": "TBL",
        "playerId": null,
        "goalieName": null,
        "confirmedStart": false,
        "statusCode": "TBD",
        "statusDescription": "From NHL API: TBD",
        "lastUpdated": "2026-01-05T14:13:58.892448Z"
      }
    },
    {
      "gameId": "2025020706",
      "gameDate": "2026-01-10",
      "startTimeUTC": "2026-01-11T00:00:00Z",
      "homeTeam": "CAR",
      "awayTeam": "SEA",
      "homeGoalie": {
        "team": "CAR",
        "playerId": null,
        "goalieName": null,
        "confirmedStart": false,
        "statusCode": "TBD",
        "statusDescription": "From NHL API: TBD",
        "lastUpdated": "2026-01-05T14:13:58.892449Z"
      },
      "awayGoalie": {
        "team": "SEA",
        "playerId": null,
        "goalieName": null,
        "confirmedStart": false,
        "statusCode": "TBD",
        "statusDescription": "From NHL API: TBD",
        "lastUpdated": "2026-01-05T14:13:58.892451Z"
      }
    },
    {
      "gameId": "2025020707",
      "gameDate": "2026-01-10",
      "startTimeUTC": "2026-01-11T01:00:00Z",
      "homeTeam": "NSH",
      "awayTeam": "CHI",
      "homeGoalie": {
        "team": "NSH",
        "playerId": null,
        "goalieName": null,
        "confirmedStart": false,
        "statusCode": "TBD",
        "statusDescription": "From NHL API: TBD",
        "lastUpdated": "2026-01-05T14:13:58.892454Z"
      },
      "awayGoalie": {
        "team": "CHI",
        "playerId": null,
        "goalieName": null,
        "confirmedStart": false,
        "statusCode": "TBD",
        "statusDescription": "From NHL API: TBD",
        "lastUpdated": "2026-01-05T14:13:58.892456Z"
      }
    },
    {
      "gameId": "2025020708",
      "gameDate": "2026-01-10",
      "startTimeUTC": "2026-01-11T01:00:00Z",
      "homeTeam": "MIN",
      "awayTeam": "NYI",
      "homeGoalie": {
        "team": "MIN",
        "playerId": null,
        "goalieName": null,
        "confirmedStart": false,
        "statusCode": "TBD",
        "statusDescription": "From NHL API: TBD",
        "lastUpdated": "2026-01-05T14:13:58.892457Z"
      },
      "awayGoalie": {
        "team": "NYI",
        "playerId": null,
        "goalieName": null,
        "confirmedStart": false,
        "statusCode": "TBD",
        "statusDescription": "From NHL API: TBD",
        "lastUpdated": "2026-01-05T14:13:58.892459Z"
      }
    },
    {
      "gameId": "2025020709",
      "gameDate": "2026-01-10",
      "startTimeUTC": "2026-01-11T03:00:00Z",
      "homeTeam": "EDM",
      "awayTeam": "LAK",
      "homeGoalie": {
        "team": "EDM",
        "playerId": null,
        "goalieName": null,
        "confirmedStart": false,
        "statusCode": "TBD",
        "statusDescription": "From NHL API: TBD",
        "lastUpdated": "2026-01-05T14:13:58.892460Z"
      },
      "awayGoalie": {
        "team": "LAK",
        "playerId": null,
        "goalieName": null,
        "confirmedStart": false,
        "statusCode": "TBD",
        "statusDescription": "From NHL API: TBD",
        "lastUpdated": "2026-01-05T14:13:58.892462Z"
      }
    },
    {
      "gameId": "2025020710",
      "gameDate": "2026-01-10",
      "startTimeUTC": "2026-01-11T03:00:00Z",
      "homeTeam": "VGK",
      "awayTeam": "STL",
      "homeGoalie": {
        "team": "VGK",
        "playerId": null,
        "goalieName": null,
        "confirmedStart": false,
        "statusCode": "TBD",
        "statusDescription": "From NHL API: TBD",
        "lastUpdated": "2026-01-05T14:13:58.892463Z"
      },
      "awayGoalie": {
        "team": "STL",
        "playerId": null,
        "goalieName": null,
        "confirmedStart": false,
        "statusCode": "TBD",
        "statusDescription": "From NHL API: TBD",
        "lastUpdated": "2026-01-05T14:13:58.892465Z"
      }
    },
    {
      "gameId": "2025020711",
      "gameDate": "2026-01-11",
      "startTimeUTC": "2026-01-11T19:00:00Z",
      "homeTeam": "WPG",
      "awayTeam": "NJD",
      "homeGoalie": {
        "team": "WPG",
        "playerId": null,
        "goalieName": null,
        "confirmedStart": false,
        "statusCode": "TBD",
        "statusDescription": "From NHL API: TBD",
        "lastUpdated": "2026-01-05T14:13:58.892467Z"
      },
      "awayGoalie": {
        "team": "NJD",
        "playerId": null,
        "goalieName": null,
        "confirmedStart": false,
        "statusCode": "TBD",
        "statusDescription": "From NHL API: TBD",
        "lastUpdated": "2026-01-05T14:13:58.892468Z"
      }
    },
    {
      "gameId": "2025020712",
      "gameDate": "2026-01-11",
      "startTimeUTC": "2026-01-11T22:00:00Z",
      "homeTeam": "BOS",
      "awayTeam": "PIT",
      "homeGoalie": {
        "team": "BOS",
        "playerId": null,
        "goalieName": null,
        "confirmedStart": false,
        "statusCode": "TBD",
        "statusDescription": "From NHL API: TBD",
        "lastUpdated": "2026-01-05T14:13:58.892470Z"
      },
      "awayGoalie": {
        "team": "PIT",
        "playerId": null,
        "goalieName": null,
        "confirmedStart": false,
        "statusCode": "TBD",
        "statusDescription": "From NHL API: TBD",
        "lastUpdated": "2026-01-05T14:13:58.892471Z"
      }
    },
    {
      "gameId": "2025020713",
      "gameDate": "2026-01-11",
      "startTimeUTC": "2026-01-12T00:00:00Z",
      "homeTeam": "NSH",
      "awayTeam": "WSH",
      "homeGoalie": {
        "team": "NSH",
        "playerId": null,
        "goalieName": null,
        "confirmedStart": false,
        "statusCode": "TBD",
        "statusDescription": "From NHL API: TBD",
        "lastUpdated": "2026-01-05T14:13:58.892473Z"
      },
      "awayGoalie": {
        "team": "WSH",
        "playerId": null,
        "goalieName": null,
        "confirmedStart": false,
        "statusCode": "TBD",
        "statusDescription": "From NHL API: TBD",
        "lastUpdated": "2026-01-05T14:13:58.892475Z"
      }
    },
    {
      "gameId": "2025020714",
      "gameDate": "2026-01-11",
      "startTimeUTC": "2026-01-12T00:00:00Z",
      "homeTeam": "UTA",
      "awayTeam": "CBJ",
      "homeGoalie": {
        "team": "UTA",
        "playerId": null,
        "goalieName": null,
        "confirmedStart": false,
        "statusCode": "TBD",
        "statusDescription": "From NHL API: TBD",
        "lastUpdated": "2026-01-05T14:13:58.892476Z"
      },
      "awayGoalie": {
        "team": "CBJ",
        "playerId": null,
        "goalieName": null,
        "confirmedStart": false,
        "statusCode": "TBD",
        "statusDescription": "From NHL API: TBD",
        "lastUpdated": "2026-01-05T14:13:58.892478Z"
      }
    },
    {
      "gameId": "2025020715",
      "gameDate": "2026-01-11",
      "startTimeUTC": "2026-01-12T01:00:00Z",
      "homeTeam": "SJS",
      "awayTeam": "VGK",
      "homeGoalie": {
        "team": "SJS",
        "playerId": null,
        "goalieName": null,
        "confirmedStart": false,
        "statusCode": "TBD",
        "statusDescription": "From NHL API: TBD",
        "lastUpdated": "2026-01-05T14:13:58.892480Z"
      },
      "awayGoalie": {
        "team": "VGK",
        "playerId": null,
        "goalieName": null,
        "confirmedStart": false,
        "statusCode": "TBD",
        "statusDescription": "From NHL API: TBD",
        "lastUpdated": "2026-01-05T14:13:58.892482Z"
      }
    }
  ]
}